{
  "updated_utc": "2026-02-14T20:28:11Z",
  "criteria": "CMC-only | Exclude stable/wrapped | MarketCap>=200000000 | Volume24h>=20000000 | Score=log(vol)+0.7log(mcap)+ratio(clamped)-penalty",
  "items": [
    {
      "symbol": "BTC",
      "name": "Bitcoin",
      "price": 69849.66339300106,
      "volume_24h": 35616103524.53286,
      "market_cap": 1396247343304.6472,
      "vol_mcap_ratio": 0.02550844855341779,
      "rank": 1
    },
    {
      "symbol": "ETH",
      "name": "Ethereum",
      "price": 2084.5121761556625,
      "volume_24h": 16421587732.166967,
      "market_cap": 251584918312.26138,
      "vol_mcap_ratio": 0.06527254432551029,
      "rank": 2
    },
    {
      "symbol": "XRP",
      "name": "XRP",
      "price": 1.4950911074126303,
      "volume_24h": 2478250264.126169,
      "market_cap": 91076936468.73102,
      "vol_mcap_ratio": 0.027210514101745333,
      "rank": 3
    },
    {
      "symbol": "SOL",
      "name": "Solana",
      "price": 87.89573001438373,
      "volume_24h": 2860275915.469125,
      "market_cap": 49921093000.27373,
      "vol_mcap_ratio": 0.057295939322751635,
      "rank": 4
    },
    {
      "symbol": "BNB",
      "name": "BNB",
      "price": 631.3499813323419,
      "volume_24h": 1442631270.7490273,
      "market_cap": 86090452899.04488,
      "vol_mcap_ratio": 0.016757157410250217,
      "rank": 5
    },
    {
      "symbol": "DOGE",
      "name": "Dogecoin",
      "price": 0.10872030052564131,
      "volume_24h": 1219680110.9587817,
      "market_cap": 18345562786.09281,
      "vol_mcap_ratio": 0.06648365739334977,
      "rank": 6
    },
    {
      "symbol": "TRX",
      "name": "TRON",
      "price": 0.2826704264546551,
      "volume_24h": 470696208.3899327,
      "market_cap": 26775498299.203342,
      "vol_mcap_ratio": 0.01757936315993557,
      "rank": 7
    },
    {
      "symbol": "USD1",
      "name": "World Liberty Financial USD",
      "price": 0.9994028983587422,
      "volume_24h": 1022379601.5125282,
      "market_cap": 5281947714.032928,
      "vol_mcap_ratio": 0.19356109845546163,
      "rank": 8
    },
    {
      "symbol": "BCH",
      "name": "Bitcoin Cash",
      "price": 567.2728717523979,
      "volume_24h": 496215433.7962408,
      "market_cap": 11342534207.03071,
      "vol_mcap_ratio": 0.04374819813094854,
      "rank": 9
    },
    {
      "symbol": "ADA",
      "name": "Cardano",
      "price": 0.2972985600561503,
      "volume_24h": 480994774.3569204,
      "market_cap": 10722413033.738293,
      "vol_mcap_ratio": 0.04485881795855658,
      "rank": 10
    },
    {
      "symbol": "LINK",
      "name": "Chainlink",
      "price": 9.11204635146016,
      "volume_24h": 571665360.5003204,
      "market_cap": 6452239752.23154,
      "vol_mcap_ratio": 0.08859952240655768,
      "rank": 11
    },
    {
      "symbol": "ZEC",
      "name": "Zcash",
      "price": 309.3667929657184,
      "volume_24h": 554354259.1678319,
      "market_cap": 5115407815.913585,
      "vol_mcap_ratio": 0.10836951404798742,
      "rank": 12
    },
    {
      "symbol": "PEPE",
      "name": "Pepe",
      "price": 4.664741593400333e-06,
      "volume_24h": 638083127.1432335,
      "market_cap": 1930141798.0333588,
      "vol_mcap_ratio": 0.3305887307312773,
      "rank": 13
    },
    {
      "symbol": "SUI",
      "name": "Sui",
      "price": 1.0285078847066549,
      "volume_24h": 515866525.3039852,
      "market_cap": 3955818770.403534,
      "vol_mcap_ratio": 0.1304070169148223,
      "rank": 14
    },
    {
      "symbol": "VBNB",
      "name": "Venus BNB",
      "price": 15.734811536284777,
      "volume_24h": 420086432.65142596,
      "market_cap": 420267233.1821097,
      "vol_mcap_ratio": 0.9995697962714942,
      "rank": 15
    },
    {
      "symbol": "LTC",
      "name": "Litecoin",
      "price": 56.183098602333736,
      "volume_24h": 302401684.47886235,
      "market_cap": 4317647010.065641,
      "vol_mcap_ratio": 0.07003853806804483,
      "rank": 16
    },
    {
      "symbol": "HYPE",
      "name": "Hyperliquid",
      "price": 31.634611953279283,
      "volume_24h": 197883672.68822095,
      "market_cap": 8203487208.749615,
      "vol_mcap_ratio": 0.024121896902230024,
      "rank": 17
    },
    {
      "symbol": "AAVE",
      "name": "Aave",
      "price": 129.70120218578433,
      "volume_24h": 352941485.80429554,
      "market_cap": 1988026593.4526768,
      "vol_mcap_ratio": 0.17753358378940468,
      "rank": 18
    },
    {
      "symbol": "UNI",
      "name": "Uniswap",
      "price": 3.6636376651968416,
      "volume_24h": 319242053.0217499,
      "market_cap": 2323426114.402243,
      "vol_mcap_ratio": 0.1374014224265025,
      "rank": 19
    },
    {
      "symbol": "HBAR",
      "name": "Hedera",
      "price": 0.10436928230030754,
      "volume_24h": 228324366.44618815,
      "market_cap": 4488206719.193543,
      "vol_mcap_ratio": 0.050872070011787306,
      "rank": 20
    }
  ]
}