{
  "updated_utc": "2026-01-28T18:39:03Z",
  "criteria": "Ranked by combined score: 24h Volume + (Volume/MarketCap ratio)",
  "items": [
    {
      "symbol": "USDT",
      "name": "Tether USDt",
      "price": 0.9988453055851974,
      "volume_24h": 91359074718.9428,
      "market_cap": 186213239245.89053,
      "vol_mcap_ratio": 0.490615356292176,
      "rank": 1
    },
    {
      "symbol": "BTC",
      "name": "Bitcoin",
      "price": 89573.01629356534,
      "volume_24h": 41729557854.31239,
      "market_cap": 1789808778596.886,
      "vol_mcap_ratio": 0.023315092848648404,
      "rank": 2
    },
    {
      "symbol": "QUQ",
      "name": "Quq",
      "price": 0.0020958464738317123,
      "volume_24h": 271034486.3030401,
      "market_cap": 2095846.4738317123,
      "vol_mcap_ratio": 129.31981883554846,
      "rank": 3
    },
    {
      "symbol": "OWL",
      "name": "Owlto Finance",
      "price": 0.06475502046393201,
      "volume_24h": 2231220126.9143815,
      "market_cap": 21369156.753097564,
      "vol_mcap_ratio": 104.4131105730672,
      "rank": 4
    },
    {
      "symbol": "ETH",
      "name": "Ethereum",
      "price": 3007.6846352468374,
      "volume_24h": 25098590423.97638,
      "market_cap": 363010613627.88556,
      "vol_mcap_ratio": 0.06914010081728467,
      "rank": 5
    },
    {
      "symbol": "TIMI",
      "name": "MetaArena",
      "price": 0.0022399184285961738,
      "volume_24h": 65130664.28388347,
      "market_cap": 892044.402941729,
      "vol_mcap_ratio": 73.01280526966997,
      "rank": 6
    },
    {
      "symbol": "USDC",
      "name": "USDC",
      "price": 0.9998126380391882,
      "volume_24h": 13245403824.201021,
      "market_cap": 71275394815.07553,
      "vol_mcap_ratio": 0.18583416982208667,
      "rank": 7
    },
    {
      "symbol": "NFLXon",
      "name": "Netflix Tokenized Stock (Ondo)",
      "price": 846.8326906868465,
      "volume_24h": 55356256.10034117,
      "market_cap": 1244196.276071121,
      "vol_mcap_ratio": 44.49157835059851,
      "rank": 8
    },
    {
      "symbol": "FDUSD",
      "name": "First Digital USD",
      "price": 0.9991128990667474,
      "volume_24h": 3190807244.726138,
      "market_cap": 467739054.95288336,
      "vol_mcap_ratio": 6.821767844567858,
      "rank": 9
    },
    {
      "symbol": "SOL",
      "name": "Solana",
      "price": 125.74695866477703,
      "volume_24h": 3689099654.526043,
      "market_cap": 71181380344.21674,
      "vol_mcap_ratio": 0.0518267507132681,
      "rank": 10
    },
    {
      "symbol": "FOGO",
      "name": "Fogo",
      "price": 0.0423848591490554,
      "volume_24h": 1416006362.2511072,
      "market_cap": 159559915.4779937,
      "vol_mcap_ratio": 8.874449187373761,
      "rank": 11
    },
    {
      "symbol": "FIGHT",
      "name": "FIGHT",
      "price": 0.020888204511865432,
      "volume_24h": 519057486.21827525,
      "market_cap": 42820819.249324135,
      "vol_mcap_ratio": 12.121615030204445,
      "rank": 12
    },
    {
      "symbol": "XRP",
      "name": "XRP",
      "price": 1.9123124383123562,
      "volume_24h": 2375504221.0535398,
      "market_cap": 116370395019.95692,
      "vol_mcap_ratio": 0.02041330375003155,
      "rank": 13
    },
    {
      "symbol": "BNB",
      "name": "BNB",
      "price": 900.9851417163428,
      "volume_24h": 1977159718.6631653,
      "market_cap": 122858585984.04375,
      "vol_mcap_ratio": 0.016092971466560333,
      "rank": 14
    },
    {
      "symbol": "USDR",
      "name": "StablR USD",
      "price": 0.9983887892378575,
      "volume_24h": 50171558.39078698,
      "market_cap": 7375110.016684963,
      "vol_mcap_ratio": 6.802821690426605,
      "rank": 15
    },
    {
      "symbol": "SPACE",
      "name": "Spacecoin",
      "price": 0.010577039829012869,
      "volume_24h": 143720994.36876452,
      "market_cap": 22767078.2319502,
      "vol_mcap_ratio": 6.312667479969982,
      "rank": 16
    },
    {
      "symbol": "USDQ",
      "name": "Quantoz USDQ",
      "price": 0.9991000131080943,
      "volume_24h": 52542209.21740501,
      "market_cap": 7972867.060503234,
      "vol_mcap_ratio": 6.590127342984775,
      "rank": 17
    },
    {
      "symbol": "MGO",
      "name": "Mango Network",
      "price": 0.0276615154650665,
      "volume_24h": 254543790.1549836,
      "market_cap": 44340387.501781836,
      "vol_mcap_ratio": 5.740675814904745,
      "rank": 18
    },
    {
      "symbol": "ELSA",
      "name": "HeyElsa",
      "price": 0.12112571971065843,
      "volume_24h": 167814907.18767273,
      "market_cap": 27735367.299346566,
      "vol_mcap_ratio": 6.050574538150299,
      "rank": 19
    },
    {
      "symbol": "USD1",
      "name": "World Liberty Financial USD",
      "price": 0.9993311957396753,
      "volume_24h": 1497847344.6823063,
      "market_cap": 5026467790.531888,
      "vol_mcap_ratio": 0.29799203080615144,
      "rank": 20
    }
  ]
}