{
  "updated_utc": "2026-01-26T13:45:12Z",
  "criteria": "Ranked by combined score: 24h Volume + (Volume/MarketCap ratio)",
  "items": [
    {
      "symbol": "USDT",
      "name": "Tether USDt",
      "price": 0.9989555530834473,
      "volume_24h": 107112269103.84125,
      "market_cap": 186678622492.06146,
      "vol_mcap_ratio": 0.5737789773352127,
      "rank": 1
    },
    {
      "symbol": "TIMI",
      "name": "MetaArena",
      "price": 0.005357231548436345,
      "volume_24h": 758749761.1884694,
      "market_cap": 2133510.0229701535,
      "vol_mcap_ratio": 355.63449574620716,
      "rank": 2
    },
    {
      "symbol": "BTC",
      "name": "Bitcoin",
      "price": 87897.93907577106,
      "volume_24h": 48108433949.40172,
      "market_cap": 1756267273575.8472,
      "vol_mcap_ratio": 0.027392433186692912,
      "rank": 3
    },
    {
      "symbol": "ETH",
      "name": "Ethereum",
      "price": 2904.9869953368243,
      "volume_24h": 32526404468.45064,
      "market_cap": 350615717054.9185,
      "vol_mcap_ratio": 0.09276938507396086,
      "rank": 4
    },
    {
      "symbol": "QUQ",
      "name": "Quq",
      "price": 0.0021900959256287086,
      "volume_24h": 278167663.34466684,
      "market_cap": 2190095.9256287087,
      "vol_mcap_ratio": 127.01163455423237,
      "rank": 5
    },
    {
      "symbol": "OWL",
      "name": "Owlto Finance",
      "price": 0.04484088758415224,
      "volume_24h": 1549277030.9222786,
      "market_cap": 14797492.90277024,
      "vol_mcap_ratio": 104.69861625223272,
      "rank": 6
    },
    {
      "symbol": "USDC",
      "name": "USDC",
      "price": 0.999703172171668,
      "volume_24h": 12591699381.454205,
      "market_cap": 72366611762.1831,
      "vol_mcap_ratio": 0.1739987416135226,
      "rank": 7
    },
    {
      "symbol": "SOL",
      "name": "Solana",
      "price": 122.78034850023178,
      "volume_24h": 6440797799.632385,
      "market_cap": 69487267916.78833,
      "vol_mcap_ratio": 0.09269033008097688,
      "rank": 8
    },
    {
      "symbol": "FDUSD",
      "name": "First Digital USD",
      "price": 0.9976859776370656,
      "volume_24h": 3769794836.509638,
      "market_cap": 495410317.62944615,
      "vol_mcap_ratio": 7.609439493606479,
      "rank": 9
    },
    {
      "symbol": "POWER",
      "name": "Power Protocol",
      "price": 0.20357164606542708,
      "volume_24h": 762261650.3541123,
      "market_cap": 42750045.67373969,
      "vol_mcap_ratio": 17.830662829498475,
      "rank": 10
    },
    {
      "symbol": "IR",
      "name": "Infrared",
      "price": 0.05693063208873336,
      "volume_24h": 231115861.60666066,
      "market_cap": 11670779.57819034,
      "vol_mcap_ratio": 19.802949756548934,
      "rank": 11
    },
    {
      "symbol": "ENSO",
      "name": "Enso",
      "price": 1.3580879236416852,
      "volume_24h": 479138371.7039199,
      "market_cap": 27963030.3477823,
      "vol_mcap_ratio": 17.134708425545142,
      "rank": 12
    },
    {
      "symbol": "XRP",
      "name": "XRP",
      "price": 1.9071293581379305,
      "volume_24h": 3462881245.40472,
      "market_cap": 116054987832.7034,
      "vol_mcap_ratio": 0.02983828019866378,
      "rank": 13
    },
    {
      "symbol": "AUCTION",
      "name": "Bounce Token",
      "price": 6.809227499286309,
      "volume_24h": 465096663.6138034,
      "market_cap": 44875162.64377199,
      "vol_mcap_ratio": 10.364233491605003,
      "rank": 14
    },
    {
      "symbol": "USDQ",
      "name": "Quantoz USDQ",
      "price": 0.9995033733342119,
      "volume_24h": 90805215.39005183,
      "market_cap": 7976085.894872304,
      "vol_mcap_ratio": 11.384683739229667,
      "rank": 15
    },
    {
      "symbol": "NOM",
      "name": "Nomina",
      "price": 0.01105220278660523,
      "volume_24h": 333269056.3066391,
      "market_cap": 32051388.081155166,
      "vol_mcap_ratio": 10.397960158941974,
      "rank": 16
    },
    {
      "symbol": "ZKC",
      "name": "Boundless",
      "price": 0.1350981855574052,
      "volume_24h": 285543799.9317858,
      "market_cap": 30906970.270768493,
      "vol_mcap_ratio": 9.238815627355436,
      "rank": 17
    },
    {
      "symbol": "ZKP",
      "name": "zkPass",
      "price": 0.11941436942641574,
      "volume_24h": 209111721.0409513,
      "market_cap": 24081897.874131966,
      "vol_mcap_ratio": 8.683357189450284,
      "rank": 18
    },
    {
      "symbol": "USD1",
      "name": "World Liberty Financial USD",
      "price": 0.9997260741936674,
      "volume_24h": 2233892683.577958,
      "market_cap": 4918969635.807519,
      "vol_mcap_ratio": 0.45413833566208484,
      "rank": 19
    },
    {
      "symbol": "BNB",
      "name": "BNB",
      "price": 872.3964658702653,
      "volume_24h": 2320808382.142321,
      "market_cap": 118960334481.8978,
      "vol_mcap_ratio": 0.01950909428970611,
      "rank": 20
    }
  ]
}