{
  "updated_utc": "2026-02-04T14:12:55Z",
  "criteria": "CMC-only | Exclude stable/wrapped | MarketCap>=200000000 | Volume24h>=20000000 | Score=log(vol)+0.7log(mcap)+ratio(clamped)-penalty",
  "items": [
    {
      "symbol": "BTC",
      "name": "Bitcoin",
      "price": 74979.72409072275,
      "volume_24h": 69284815620.74939,
      "market_cap": 1498334822449.731,
      "vol_mcap_ratio": 0.04624121029735588,
      "rank": 1
    },
    {
      "symbol": "ETH",
      "name": "Ethereum",
      "price": 2192.324804251203,
      "volume_24h": 47463860795.87019,
      "market_cap": 264599523651.48526,
      "vol_mcap_ratio": 0.1793799933607846,
      "rank": 2
    },
    {
      "symbol": "SOL",
      "name": "Solana",
      "price": 94.2355048102834,
      "volume_24h": 6690172832.2628145,
      "market_cap": 53388633221.88019,
      "vol_mcap_ratio": 0.12531080922148408,
      "rank": 3
    },
    {
      "symbol": "XRP",
      "name": "XRP",
      "price": 1.56623763392211,
      "volume_24h": 4169060556.138769,
      "market_cap": 95310624196.6867,
      "vol_mcap_ratio": 0.04374182407551265,
      "rank": 4
    },
    {
      "symbol": "BNB",
      "name": "BNB",
      "price": 740.4825948122464,
      "volume_24h": 2772559927.1942053,
      "market_cap": 100972084049.10918,
      "vol_mcap_ratio": 0.027458677844519205,
      "rank": 5
    },
    {
      "symbol": "DOGE",
      "name": "Dogecoin",
      "price": 0.10586129989801539,
      "volume_24h": 1947769467.4144497,
      "market_cap": 17848336175.671005,
      "vol_mcap_ratio": 0.1091289097338634,
      "rank": 6
    },
    {
      "symbol": "USD1",
      "name": "World Liberty Financial USD",
      "price": 0.9996622201621886,
      "volume_24h": 2352663724.7400856,
      "market_cap": 5116837726.867511,
      "vol_mcap_ratio": 0.4597886136561865,
      "rank": 7
    },
    {
      "symbol": "TRX",
      "name": "TRON",
      "price": 0.2842641642469809,
      "volume_24h": 796681034.130154,
      "market_cap": 26924916129.923004,
      "vol_mcap_ratio": 0.02958898851479662,
      "rank": 8
    },
    {
      "symbol": "LINK",
      "name": "Chainlink",
      "price": 9.413764203790972,
      "volume_24h": 1042213889.7572347,
      "market_cap": 6665886154.552005,
      "vol_mcap_ratio": 0.15635038846943508,
      "rank": 9
    },
    {
      "symbol": "ADA",
      "name": "Cardano",
      "price": 0.29165804778071686,
      "volume_24h": 819539078.1571314,
      "market_cap": 10516415646.513906,
      "vol_mcap_ratio": 0.07792950618386797,
      "rank": 10
    },
    {
      "symbol": "HYPE",
      "name": "Hyperliquid",
      "price": 32.78775910505941,
      "volume_24h": 871055776.5999873,
      "market_cap": 8538572528.5656185,
      "vol_mcap_ratio": 0.10201421533703534,
      "rank": 11
    },
    {
      "symbol": "XAUT",
      "name": "Tether Gold",
      "price": 5028.076743665812,
      "volume_24h": 1029275003.3673059,
      "market_cap": 2613723219.787899,
      "vol_mcap_ratio": 0.39379647989308925,
      "rank": 12
    },
    {
      "symbol": "SUI",
      "name": "Sui",
      "price": 1.103352159320595,
      "volume_24h": 982992900.6221265,
      "market_cap": 4243682763.2590723,
      "vol_mcap_ratio": 0.23163675407895135,
      "rank": 13
    },
    {
      "symbol": "BCH",
      "name": "Bitcoin Cash",
      "price": 523.0318346369487,
      "volume_24h": 612027125.412257,
      "market_cap": 10455506077.336082,
      "vol_mcap_ratio": 0.05853634638871474,
      "rank": 14
    },
    {
      "symbol": "PAXG",
      "name": "PAX Gold",
      "price": 5059.651981899459,
      "volume_24h": 809896536.7806075,
      "market_cap": 2273952923.989841,
      "vol_mcap_ratio": 0.3561624025881662,
      "rank": 15
    },
    {
      "symbol": "LTC",
      "name": "Litecoin",
      "price": 59.36396763723214,
      "volume_24h": 498785065.1357853,
      "market_cap": 4559862231.699423,
      "vol_mcap_ratio": 0.10938599453034181,
      "rank": 16
    },
    {
      "symbol": "AVAX",
      "name": "Avalanche",
      "price": 9.878053855579921,
      "volume_24h": 452820429.65008235,
      "market_cap": 4264769091.9736934,
      "vol_mcap_ratio": 0.10617700979457284,
      "rank": 17
    },
    {
      "symbol": "ZEC",
      "name": "Zcash",
      "price": 273.90618763703986,
      "volume_24h": 395681313.75944823,
      "market_cap": 4524640472.361124,
      "vol_mcap_ratio": 0.087450332501881,
      "rank": 18
    },
    {
      "symbol": "PEPE",
      "name": "Pepe",
      "price": 4.11972175424048e-06,
      "volume_24h": 513544847.3032674,
      "market_cap": 1704627575.8075938,
      "vol_mcap_ratio": 0.3012651294579507,
      "rank": 19
    },
    {
      "symbol": "VBNB",
      "name": "Venus BNB",
      "price": 18.45722491400856,
      "volume_24h": 470271284.5089866,
      "market_cap": 470272859.63046396,
      "vol_mcap_ratio": 0.9999966506221971,
      "rank": 20
    }
  ]
}