{
  "updated_utc": "2026-02-15T02:25:02Z",
  "criteria": "CMC-only | Exclude stable/wrapped | MarketCap>=200000000 | Volume24h>=20000000 | Score=log(vol)+0.7log(mcap)+ratio(clamped)-penalty",
  "items": [
    {
      "symbol": "BTC",
      "name": "Bitcoin",
      "price": 69391.79617331819,
      "volume_24h": 36153211789.65548,
      "market_cap": 1387104464542.901,
      "vol_mcap_ratio": 0.026063798880186877,
      "rank": 1
    },
    {
      "symbol": "ETH",
      "name": "Ethereum",
      "price": 2053.373002332487,
      "volume_24h": 18039928267.16858,
      "market_cap": 247826634637.00345,
      "vol_mcap_ratio": 0.07279253214083312,
      "rank": 2
    },
    {
      "symbol": "XRP",
      "name": "XRP",
      "price": 1.5271015292920296,
      "volume_24h": 3031521239.248386,
      "market_cap": 93026925432.87692,
      "vol_mcap_ratio": 0.03258756779439909,
      "rank": 3
    },
    {
      "symbol": "SOL",
      "name": "Solana",
      "price": 87.96972283933265,
      "volume_24h": 2991337933.2858963,
      "market_cap": 49963105670.2583,
      "vol_mcap_ratio": 0.05987093662727535,
      "rank": 4
    },
    {
      "symbol": "BNB",
      "name": "BNB",
      "price": 630.061673324029,
      "volume_24h": 1408109008.019844,
      "market_cap": 85914776292.03336,
      "vol_mcap_ratio": 0.01638960221735937,
      "rank": 5
    },
    {
      "symbol": "DOGE",
      "name": "Dogecoin",
      "price": 0.11286848340115174,
      "volume_24h": 1848902680.6682336,
      "market_cap": 19045915833.850883,
      "vol_mcap_ratio": 0.09707607115338202,
      "rank": 6
    },
    {
      "symbol": "USD1",
      "name": "World Liberty Financial USD",
      "price": 0.9995148461014759,
      "volume_24h": 1050302695.09222,
      "market_cap": 5282538370.441915,
      "vol_mcap_ratio": 0.19882537928529162,
      "rank": 7
    },
    {
      "symbol": "TRX",
      "name": "TRON",
      "price": 0.28162413138050063,
      "volume_24h": 450114610.10135233,
      "market_cap": 26676566431.599136,
      "vol_mcap_ratio": 0.016873033913696593,
      "rank": 8
    },
    {
      "symbol": "PEPE",
      "name": "Pepe",
      "price": 4.781640948250503e-06,
      "volume_24h": 937326210.7807165,
      "market_cap": 1978511536.5154798,
      "vol_mcap_ratio": 0.473753219772233,
      "rank": 9
    },
    {
      "symbol": "ADA",
      "name": "Cardano",
      "price": 0.29528742781746786,
      "volume_24h": 544664316.8029529,
      "market_cap": 10649879246.408321,
      "vol_mcap_ratio": 0.05114276924657538,
      "rank": 10
    },
    {
      "symbol": "ZEC",
      "name": "Zcash",
      "price": 324.85691020113137,
      "volume_24h": 625156485.8429936,
      "market_cap": 5371684364.864247,
      "vol_mcap_ratio": 0.11637997383690143,
      "rank": 11
    },
    {
      "symbol": "LINK",
      "name": "Chainlink",
      "price": 9.04329343517528,
      "volume_24h": 555569686.9915882,
      "market_cap": 6403555814.241686,
      "vol_mcap_ratio": 0.08675956032990075,
      "rank": 12
    },
    {
      "symbol": "BCH",
      "name": "Bitcoin Cash",
      "price": 562.4381882472004,
      "volume_24h": 383212769.5119038,
      "market_cap": 11245918179.235344,
      "vol_mcap_ratio": 0.03407572093308259,
      "rank": 13
    },
    {
      "symbol": "SUI",
      "name": "Sui",
      "price": 1.0230501804146062,
      "volume_24h": 576740401.3899561,
      "market_cap": 3934827498.0926213,
      "vol_mcap_ratio": 0.14657323648102155,
      "rank": 14
    },
    {
      "symbol": "VBNB",
      "name": "Venus BNB",
      "price": 15.719699303299471,
      "volume_24h": 420406788.2828548,
      "market_cap": 419679824.6394961,
      "vol_mcap_ratio": 1.0017321863017437,
      "rank": 15
    },
    {
      "symbol": "LTC",
      "name": "Litecoin",
      "price": 55.730994504395696,
      "volume_24h": 298910869.00509256,
      "market_cap": 4282953510.4260297,
      "vol_mcap_ratio": 0.06979082735253869,
      "rank": 16
    },
    {
      "symbol": "HYPE",
      "name": "Hyperliquid",
      "price": 31.3251628140668,
      "volume_24h": 205052173.41521063,
      "market_cap": 8122591879.2991705,
      "vol_mcap_ratio": 0.02524467269342884,
      "rank": 17
    },
    {
      "symbol": "AAVE",
      "name": "Aave",
      "price": 127.96346776615918,
      "volume_24h": 368187162.38604105,
      "market_cap": 1961395749.352847,
      "vol_mcap_ratio": 0.18771691664342732,
      "rank": 18
    },
    {
      "symbol": "UNI",
      "name": "Uniswap",
      "price": 3.6315739589957827,
      "volume_24h": 330484389.5473688,
      "market_cap": 2303077248.5455494,
      "vol_mcap_ratio": 0.14349687565021013,
      "rank": 19
    },
    {
      "symbol": "AVAX",
      "name": "Avalanche",
      "price": 9.545390547765514,
      "volume_24h": 230149513.12751776,
      "market_cap": 4121431997.011137,
      "vol_mcap_ratio": 0.05584212314904679,
      "rank": 20
    }
  ]
}