{
  "updated_utc": "2026-02-14T19:25:02Z",
  "criteria": "CMC-only | Exclude stable/wrapped | MarketCap>=200000000 | Volume24h>=20000000 | Score=log(vol)+0.7log(mcap)+ratio(clamped)-penalty",
  "items": [
    {
      "symbol": "BTC",
      "name": "Bitcoin",
      "price": 69735.60587489036,
      "volume_24h": 35805287709.082054,
      "market_cap": 1393967410962.6692,
      "vol_mcap_ratio": 0.025685885787211513,
      "rank": 1
    },
    {
      "symbol": "ETH",
      "name": "Ethereum",
      "price": 2082.935838041028,
      "volume_24h": 16808467321.921375,
      "market_cap": 251394666175.4117,
      "vol_mcap_ratio": 0.06686087488504308,
      "rank": 2
    },
    {
      "symbol": "XRP",
      "name": "XRP",
      "price": 1.4929377872250824,
      "volume_24h": 2394555649.6035213,
      "market_cap": 90945761983.81448,
      "vol_mcap_ratio": 0.026329491307463867,
      "rank": 3
    },
    {
      "symbol": "SOL",
      "name": "Solana",
      "price": 87.90831071285642,
      "volume_24h": 2909218058.1568427,
      "market_cap": 49928241138.662544,
      "vol_mcap_ratio": 0.05826798604976401,
      "rank": 4
    },
    {
      "symbol": "BNB",
      "name": "BNB",
      "price": 631.4151283735315,
      "volume_24h": 1458250185.8613772,
      "market_cap": 86099336898.68402,
      "vol_mcap_ratio": 0.016936834107994923,
      "rank": 5
    },
    {
      "symbol": "DOGE",
      "name": "Dogecoin",
      "price": 0.1081639867593052,
      "volume_24h": 1121182820.131907,
      "market_cap": 18251632566.263386,
      "vol_mcap_ratio": 0.06142917988631436,
      "rank": 6
    },
    {
      "symbol": "TRX",
      "name": "TRON",
      "price": 0.2830235976776051,
      "volume_24h": 478836764.6557208,
      "market_cap": 26808920458.28555,
      "vol_mcap_ratio": 0.01786109833854693,
      "rank": 7
    },
    {
      "symbol": "USD1",
      "name": "World Liberty Financial USD",
      "price": 0.9996079832705163,
      "volume_24h": 1053674726.846393,
      "market_cap": 5281372259.757097,
      "vol_mcap_ratio": 0.19950775575415583,
      "rank": 8
    },
    {
      "symbol": "BCH",
      "name": "Bitcoin Cash",
      "price": 568.4139273663149,
      "volume_24h": 511072421.9051503,
      "market_cap": 11365331676.371607,
      "vol_mcap_ratio": 0.044967664513272755,
      "rank": 9
    },
    {
      "symbol": "ADA",
      "name": "Cardano",
      "price": 0.29468890557190053,
      "volume_24h": 444779789.15626436,
      "market_cap": 10628292856.196268,
      "vol_mcap_ratio": 0.041848657651257594,
      "rank": 10
    },
    {
      "symbol": "LINK",
      "name": "Chainlink",
      "price": 9.134080205899968,
      "volume_24h": 565169158.1378335,
      "market_cap": 6467841923.909324,
      "vol_mcap_ratio": 0.08738141172693213,
      "rank": 11
    },
    {
      "symbol": "ZEC",
      "name": "Zcash",
      "price": 298.7606432192968,
      "volume_24h": 519537266.820816,
      "market_cap": 4940034173.547234,
      "vol_mcap_ratio": 0.10516875968243714,
      "rank": 12
    },
    {
      "symbol": "SUI",
      "name": "Sui",
      "price": 1.032774838417868,
      "volume_24h": 498706356.75167584,
      "market_cap": 3972230210.543416,
      "vol_mcap_ratio": 0.12554820096478017,
      "rank": 13
    },
    {
      "symbol": "PEPE",
      "name": "Pepe",
      "price": 4.648174319081458e-06,
      "volume_24h": 575484867.4049718,
      "market_cap": 1923286715.4951134,
      "vol_mcap_ratio": 0.29921948858094427,
      "rank": 14
    },
    {
      "symbol": "VBNB",
      "name": "Venus BNB",
      "price": 15.723744316022211,
      "volume_24h": 419971965.2135423,
      "market_cap": 419971634.4691515,
      "vol_mcap_ratio": 1.0000007875398327,
      "rank": 15
    },
    {
      "symbol": "LTC",
      "name": "Litecoin",
      "price": 56.07205001805334,
      "volume_24h": 308084862.88042325,
      "market_cap": 4309104913.675943,
      "vol_mcap_ratio": 0.07149625480285814,
      "rank": 16
    },
    {
      "symbol": "HYPE",
      "name": "Hyperliquid",
      "price": 31.061466395822,
      "volume_24h": 199126539.9683135,
      "market_cap": 8054849957.001058,
      "vol_mcap_ratio": 0.02472132206450824,
      "rank": 17
    },
    {
      "symbol": "AAVE",
      "name": "Aave",
      "price": 129.43499563750922,
      "volume_24h": 352512522.0173715,
      "market_cap": 1983946118.109555,
      "vol_mcap_ratio": 0.17768250800746066,
      "rank": 18
    },
    {
      "symbol": "UNI",
      "name": "Uniswap",
      "price": 3.668892178290281,
      "volume_24h": 322199652.71842945,
      "market_cap": 2326758450.745365,
      "vol_mcap_ratio": 0.1384757634017465,
      "rank": 19
    },
    {
      "symbol": "HBAR",
      "name": "Hedera",
      "price": 0.10435958304510672,
      "volume_24h": 222213644.4898969,
      "market_cap": 4487789620.776984,
      "vol_mcap_ratio": 0.049515165207638316,
      "rank": 20
    }
  ]
}