{
  "updated_utc": "2026-01-31T21:22:42Z",
  "criteria": "Ranked by combined score: 24h Volume + (Volume/MarketCap ratio)",
  "items": [
    {
      "symbol": "USDT",
      "name": "Tether USDt",
      "price": 0.9987915632499432,
      "volume_24h": 144512095981.18536,
      "market_cap": 185149039003.9622,
      "vol_mcap_ratio": 0.7805176670568233,
      "rank": 1
    },
    {
      "symbol": "BTC",
      "name": "Bitcoin",
      "price": 77556.01340614104,
      "volume_24h": 66897240634.12182,
      "market_cap": 1549775136626.3047,
      "vol_mcap_ratio": 0.043165772280841966,
      "rank": 2
    },
    {
      "symbol": "ETH",
      "name": "Ethereum",
      "price": 2392.8693587100947,
      "volume_24h": 45307332152.76313,
      "market_cap": 288805341024.64,
      "vol_mcap_ratio": 0.15687844273246193,
      "rank": 3
    },
    {
      "symbol": "OWL",
      "name": "Owlto Finance",
      "price": 0.04834577576905322,
      "volume_24h": 2328303516.580395,
      "market_cap": 15954106.003787562,
      "vol_mcap_ratio": 145.9375734389409,
      "rank": 4
    },
    {
      "symbol": "QUQ",
      "name": "Quq",
      "price": 0.0021567154114933065,
      "volume_24h": 254281057.49603766,
      "market_cap": 2156715.4114933065,
      "vol_mcap_ratio": 117.90199863225062,
      "rank": 5
    },
    {
      "symbol": "USDC",
      "name": "USDC",
      "price": 0.9997908250365793,
      "volume_24h": 18328820290.025932,
      "market_cap": 70113471971.94196,
      "vol_mcap_ratio": 0.2614165263041141,
      "rank": 6
    },
    {
      "symbol": "SOL",
      "name": "Solana",
      "price": 101.92733557759333,
      "volume_24h": 8971848989.068378,
      "market_cap": 57722360195.526405,
      "vol_mcap_ratio": 0.1554310835294589,
      "rank": 7
    },
    {
      "symbol": "XRP",
      "name": "XRP",
      "price": 1.5944860857721108,
      "volume_24h": 5934391568.308921,
      "market_cap": 97029633828.49557,
      "vol_mcap_ratio": 0.06116060974524789,
      "rank": 8
    },
    {
      "symbol": "FIGHT",
      "name": "FIGHT",
      "price": 0.007295360431291157,
      "volume_24h": 274092379.92444664,
      "market_cap": 14955488.884146873,
      "vol_mcap_ratio": 18.327209631708545,
      "rank": 9
    },
    {
      "symbol": "ELSA",
      "name": "HeyElsa",
      "price": 0.12442501275922653,
      "volume_24h": 334157175.61030084,
      "market_cap": 28490839.42160769,
      "vol_mcap_ratio": 11.728583025071323,
      "rank": 10
    },
    {
      "symbol": "ENSO",
      "name": "Enso",
      "price": 1.4088847085588343,
      "volume_24h": 332883747.03215057,
      "market_cap": 29008936.149226397,
      "vol_mcap_ratio": 11.475213889945696,
      "rank": 11
    },
    {
      "symbol": "BNB",
      "name": "BNB",
      "price": 769.7219644207152,
      "volume_24h": 3151460210.779072,
      "market_cap": 104959335668.65353,
      "vol_mcap_ratio": 0.030025535038902366,
      "rank": 12
    },
    {
      "symbol": "FDUSD",
      "name": "First Digital USD",
      "price": 0.9967541392705342,
      "volume_24h": 1963661458.858011,
      "market_cap": 454662155.6317728,
      "vol_mcap_ratio": 4.318946352879135,
      "rank": 13
    },
    {
      "symbol": "USD1",
      "name": "World Liberty Financial USD",
      "price": 0.99860811520445,
      "volume_24h": 2536995527.5734377,
      "market_cap": 5045291342.371537,
      "vol_mcap_ratio": 0.5028442076807648,
      "rank": 14
    },
    {
      "symbol": "IMU",
      "name": "Immunefi",
      "price": 0.004841714436310578,
      "volume_24h": 42320781.14679042,
      "market_cap": 4059275.7428583256,
      "vol_mcap_ratio": 10.425697544998602,
      "rank": 15
    },
    {
      "symbol": "DOGE",
      "name": "Dogecoin",
      "price": 0.10161092253584471,
      "volume_24h": 2501555968.2322774,
      "market_cap": 17126572116.572483,
      "vol_mcap_ratio": 0.1460628519942793,
      "rank": 16
    },
    {
      "symbol": "WETH",
      "name": "WETH",
      "price": 2385.480521810746,
      "volume_24h": 2454893891.909203,
      "market_cap": 8051754372.184318,
      "vol_mcap_ratio": 0.3048893170896901,
      "rank": 17
    },
    {
      "symbol": "SPACE",
      "name": "Spacecoin",
      "price": 0.007182858663560901,
      "volume_24h": 127286029.03892054,
      "market_cap": 15461103.27331484,
      "vol_mcap_ratio": 8.232661459458098,
      "rank": 18
    },
    {
      "symbol": "SOL",
      "name": "Wrapped Solana",
      "price": 101.91262828675586,
      "volume_24h": 924132080.1391649,
      "market_cap": 189557652.4854836,
      "vol_mcap_ratio": 4.875203232483243,
      "rank": 19
    },
    {
      "symbol": "USDQ",
      "name": "Quantoz USDQ",
      "price": 0.9989525246784006,
      "volume_24h": 56983107.08230991,
      "market_cap": 7971690.095607346,
      "vol_mcap_ratio": 7.148183935764062,
      "rank": 20
    }
  ]
}