{
  "updated_utc": "2026-02-23T16:28:47Z",
  "criteria": "CMC-only | Exclude stable/wrapped | MarketCap>=200000000 | Volume24h>=20000000 | Score=log(vol)+0.7log(mcap)+ratio(clamped)-penalty",
  "items": [
    {
      "symbol": "BTC",
      "name": "Bitcoin",
      "price": 65574.66660232091,
      "volume_24h": 41864628582.80961,
      "market_cap": 1311078113257.4924,
      "vol_mcap_ratio": 0.03193145256524277,
      "rank": 1
    },
    {
      "symbol": "ETH",
      "name": "Ethereum",
      "price": 1890.7272146965015,
      "volume_24h": 20091818978.55203,
      "market_cap": 228196320334.7318,
      "vol_mcap_ratio": 0.08804620052190221,
      "rank": 2
    },
    {
      "symbol": "XRP",
      "name": "XRP",
      "price": 1.371727961437681,
      "volume_24h": 3255938515.381718,
      "market_cap": 83700897808.58415,
      "vol_mcap_ratio": 0.038899684479224275,
      "rank": 3
    },
    {
      "symbol": "SOL",
      "name": "Solana",
      "price": 79.44072221465089,
      "volume_24h": 4264047871.3766785,
      "market_cap": 45169666706.22381,
      "vol_mcap_ratio": 0.0944006937024653,
      "rank": 4
    },
    {
      "symbol": "USD1",
      "name": "World Liberty Financial USD",
      "price": 0.9989344320508776,
      "volume_24h": 4355645256.790329,
      "market_cap": 4833148260.943404,
      "vol_mcap_ratio": 0.9012024919633089,
      "rank": 5
    },
    {
      "symbol": "BNB",
      "name": "BNB",
      "price": 604.4291239844252,
      "volume_24h": 1909476626.8647096,
      "market_cap": 82419352621.88237,
      "vol_mcap_ratio": 0.023167818796452702,
      "rank": 6
    },
    {
      "symbol": "DOGE",
      "name": "Dogecoin",
      "price": 0.09499616801796211,
      "volume_24h": 948657909.0301431,
      "market_cap": 16041119725.843729,
      "vol_mcap_ratio": 0.05913913275653491,
      "rank": 7
    },
    {
      "symbol": "TRX",
      "name": "TRON",
      "price": 0.2834241332968299,
      "volume_24h": 590827043.7810204,
      "market_cap": 26850346375.7886,
      "vol_mcap_ratio": 0.022004447745738537,
      "rank": 8
    },
    {
      "symbol": "LINK",
      "name": "Chainlink",
      "price": 8.422894000867066,
      "volume_24h": 649145812.063679,
      "market_cap": 5964250993.139238,
      "vol_mcap_ratio": 0.10883945239903561,
      "rank": 9
    },
    {
      "symbol": "BCH",
      "name": "Bitcoin Cash",
      "price": 532.4121035562393,
      "volume_24h": 433470005.7308649,
      "market_cap": 10647759572.65594,
      "vol_mcap_ratio": 0.04070997309556471,
      "rank": 10
    },
    {
      "symbol": "ADA",
      "name": "Cardano",
      "price": 0.2673942135415737,
      "volume_24h": 432823310.7673175,
      "market_cap": 9644858260.241652,
      "vol_mcap_ratio": 0.04487606754694528,
      "rank": 11
    },
    {
      "symbol": "SUI",
      "name": "Sui",
      "price": 0.88784567558091,
      "volume_24h": 505333058.52410305,
      "market_cap": 3414807646.0165277,
      "vol_mcap_ratio": 0.14798287660904963,
      "rank": 12
    },
    {
      "symbol": "XAUT",
      "name": "Tether Gold",
      "price": 5197.4172001421475,
      "volume_24h": 489292908.60029364,
      "market_cap": 2706948148.4310594,
      "vol_mcap_ratio": 0.18075444440407423,
      "rank": 13
    },
    {
      "symbol": "WLFI",
      "name": "World Liberty Financial",
      "price": 0.11386459929181583,
      "volume_24h": 385198941.1005267,
      "market_cap": 3149573904.826596,
      "vol_mcap_ratio": 0.12230192170128942,
      "rank": 14
    },
    {
      "symbol": "HYPE",
      "name": "Hyperliquid",
      "price": 26.517707258709056,
      "volume_24h": 238886225.19313183,
      "market_cap": 6862904799.347479,
      "vol_mcap_ratio": 0.03480832565473515,
      "rank": 15
    },
    {
      "symbol": "VBNB",
      "name": "Venus BNB",
      "price": 15.069632749149125,
      "volume_24h": 404735280.02560323,
      "market_cap": 404722398.1999794,
      "vol_mcap_ratio": 1.000031828793467,
      "rank": 16
    },
    {
      "symbol": "ZEC",
      "name": "Zcash",
      "price": 242.13126633422883,
      "volume_24h": 302882536.2479475,
      "market_cap": 4007022921.112285,
      "vol_mcap_ratio": 0.07558792205857215,
      "rank": 17
    },
    {
      "symbol": "LTC",
      "name": "Litecoin",
      "price": 52.11242036363722,
      "volume_24h": 285267705.4634281,
      "market_cap": 4006483755.171486,
      "vol_mcap_ratio": 0.07120151307120876,
      "rank": 18
    },
    {
      "symbol": "PAXG",
      "name": "PAX Gold",
      "price": 5232.956691132095,
      "volume_24h": 334979610.7580186,
      "market_cap": 2404110572.4090066,
      "vol_mcap_ratio": 0.1393361913559395,
      "rank": 19
    },
    {
      "symbol": "AAVE",
      "name": "Aave",
      "price": 116.40050312311752,
      "volume_24h": 358939875.8957707,
      "market_cap": 1784326063.8349671,
      "vol_mcap_ratio": 0.20116271525189647,
      "rank": 20
    }
  ]
}