{
  "updated_utc": "2026-02-24T15:59:02Z",
  "criteria": "CMC-only | Exclude stable/wrapped | MarketCap>=200000000 | Volume24h>=20000000 | Score=log(vol)+0.7log(mcap)+ratio(clamped)-penalty",
  "items": [
    {
      "symbol": "BTC",
      "name": "Bitcoin",
      "price": 63954.83419302544,
      "volume_24h": 44495009021.56533,
      "market_cap": 1278722100396.6401,
      "vol_mcap_ratio": 0.03479646516452922,
      "rank": 1
    },
    {
      "symbol": "ETH",
      "name": "Ethereum",
      "price": 1845.5635641215072,
      "volume_24h": 20453673406.53976,
      "market_cap": 222745385349.0505,
      "vol_mcap_ratio": 0.09182535195729453,
      "rank": 2
    },
    {
      "symbol": "SOL",
      "name": "Solana",
      "price": 77.20211255247867,
      "volume_24h": 3938995226.38822,
      "market_cap": 43902287585.792885,
      "vol_mcap_ratio": 0.08972186742412276,
      "rank": 3
    },
    {
      "symbol": "XRP",
      "name": "XRP",
      "price": 1.3492925236911808,
      "volume_24h": 2806651977.5276117,
      "market_cap": 82331919166.38858,
      "vol_mcap_ratio": 0.0340894759401334,
      "rank": 4
    },
    {
      "symbol": "BNB",
      "name": "BNB",
      "price": 585.2838925064116,
      "volume_24h": 1831100697.2512884,
      "market_cap": 79808701523.21461,
      "vol_mcap_ratio": 0.02294362221541295,
      "rank": 5
    },
    {
      "symbol": "USD1",
      "name": "World Liberty Financial USD",
      "price": 0.9999758919833899,
      "volume_24h": 2963080515.5815973,
      "market_cap": 4714092995.457837,
      "vol_mcap_ratio": 0.6285579258696444,
      "rank": 6
    },
    {
      "symbol": "DOGE",
      "name": "Dogecoin",
      "price": 0.0917960467073771,
      "volume_24h": 879930030.6633804,
      "market_cap": 15501966796.629665,
      "vol_mcap_ratio": 0.05676247680098818,
      "rank": 7
    },
    {
      "symbol": "TRX",
      "name": "TRON",
      "price": 0.28158448743927766,
      "volume_24h": 512891829.2357614,
      "market_cap": 26676305904.593914,
      "vol_mcap_ratio": 0.01922649376829333,
      "rank": 8
    },
    {
      "symbol": "BCH",
      "name": "Bitcoin Cash",
      "price": 475.492083089994,
      "volume_24h": 583175685.4964134,
      "market_cap": 9509572711.590384,
      "vol_mcap_ratio": 0.06132511976964346,
      "rank": 9
    },
    {
      "symbol": "LINK",
      "name": "Chainlink",
      "price": 8.205545046121998,
      "volume_24h": 595156442.8845999,
      "market_cap": 5810346204.706355,
      "vol_mcap_ratio": 0.10243046144178565,
      "rank": 10
    },
    {
      "symbol": "ADA",
      "name": "Cardano",
      "price": 0.2594867556984158,
      "volume_24h": 404113873.9686077,
      "market_cap": 9360760642.53204,
      "vol_mcap_ratio": 0.04317105087939701,
      "rank": 11
    },
    {
      "symbol": "XAUT",
      "name": "Tether Gold",
      "price": 5134.171173954736,
      "volume_24h": 594203605.0257109,
      "market_cap": 2674007996.2572155,
      "vol_mcap_ratio": 0.22221459541535116,
      "rank": 12
    },
    {
      "symbol": "PAXG",
      "name": "PAX Gold",
      "price": 5168.369555936872,
      "volume_24h": 577608159.977923,
      "market_cap": 2403673382.888004,
      "vol_mcap_ratio": 0.24030226572793728,
      "rank": 13
    },
    {
      "symbol": "SUI",
      "name": "Sui",
      "price": 0.8658894704423072,
      "volume_24h": 458411947.8083921,
      "market_cap": 3330360293.0058236,
      "vol_mcap_ratio": 0.1376463527898513,
      "rank": 14
    },
    {
      "symbol": "LTC",
      "name": "Litecoin",
      "price": 51.2815287503102,
      "volume_24h": 322309213.4024251,
      "market_cap": 3942783003.7594805,
      "vol_mcap_ratio": 0.08174662746975937,
      "rank": 15
    },
    {
      "symbol": "HYPE",
      "name": "Hyperliquid",
      "price": 26.756283989750955,
      "volume_24h": 219564163.05045667,
      "market_cap": 6921910784.176958,
      "vol_mcap_ratio": 0.03172016656908757,
      "rank": 16
    },
    {
      "symbol": "VBNB",
      "name": "Venus BNB",
      "price": 14.576998584441865,
      "volume_24h": 391768151.1299902,
      "market_cap": 391795319.0791966,
      "vol_mcap_ratio": 0.9999306578004296,
      "rank": 17
    },
    {
      "symbol": "ZEC",
      "name": "Zcash",
      "price": 238.392514125308,
      "volume_24h": 275487914.4471282,
      "market_cap": 3945537872.588136,
      "vol_mcap_ratio": 0.06982265114247088,
      "rank": 18
    },
    {
      "symbol": "AAVE",
      "name": "Aave",
      "price": 114.88814771693114,
      "volume_24h": 363359708.5641108,
      "market_cap": 1761145659.137555,
      "vol_mcap_ratio": 0.20632007731947088,
      "rank": 19
    },
    {
      "symbol": "AVAX",
      "name": "Avalanche",
      "price": 8.318760318979155,
      "volume_24h": 275329129.16884327,
      "market_cap": 3591807457.4887986,
      "vol_mcap_ratio": 0.07665475736868668,
      "rank": 20
    }
  ]
}