{
  "updated_utc": "2026-02-21T16:30:20Z",
  "criteria": "CMC-only | Exclude stable/wrapped | MarketCap>=200000000 | Volume24h>=20000000 | Score=log(vol)+0.7log(mcap)+ratio(clamped)-penalty",
  "items": [
    {
      "symbol": "BTC",
      "name": "Bitcoin",
      "price": 68218.60526052631,
      "volume_24h": 29586272263.203846,
      "market_cap": 1363877042792.1506,
      "vol_mcap_ratio": 0.021692770927967495,
      "rank": 1
    },
    {
      "symbol": "ETH",
      "name": "Ethereum",
      "price": 1981.2421611987047,
      "volume_24h": 14512943653.251154,
      "market_cap": 239120816952.10233,
      "vol_mcap_ratio": 0.06069293271174381,
      "rank": 2
    },
    {
      "symbol": "SOL",
      "name": "Solana",
      "price": 86.02911331605326,
      "volume_24h": 2584536972.4679227,
      "market_cap": 48905467685.95785,
      "vol_mcap_ratio": 0.0528476077371205,
      "rank": 3
    },
    {
      "symbol": "XRP",
      "name": "XRP",
      "price": 1.4416483134581217,
      "volume_24h": 1810120419.980241,
      "market_cap": 87967338680.04482,
      "vol_mcap_ratio": 0.02057718747823006,
      "rank": 4
    },
    {
      "symbol": "BNB",
      "name": "BNB",
      "price": 624.5723902028404,
      "volume_24h": 1433083439.8646536,
      "market_cap": 85166108633.11105,
      "vol_mcap_ratio": 0.01682692168123197,
      "rank": 5
    },
    {
      "symbol": "USD1",
      "name": "World Liberty Financial USD",
      "price": 0.9991781773814046,
      "volume_24h": 1587959349.9392478,
      "market_cap": 5023363286.198545,
      "vol_mcap_ratio": 0.31611477400053695,
      "rank": 6
    },
    {
      "symbol": "DOGE",
      "name": "Dogecoin",
      "price": 0.09958854766795609,
      "volume_24h": 653640512.085827,
      "market_cap": 16813876402.870996,
      "vol_mcap_ratio": 0.038875063454981554,
      "rank": 7
    },
    {
      "symbol": "TRX",
      "name": "TRON",
      "price": 0.2874491720905021,
      "volume_24h": 422894551.97416115,
      "market_cap": 27230696125.219646,
      "vol_mcap_ratio": 0.015530067613016266,
      "rank": 8
    },
    {
      "symbol": "LINK",
      "name": "Chainlink",
      "price": 8.861130571438562,
      "volume_24h": 518411991.5676467,
      "market_cap": 6274566295.812158,
      "vol_mcap_ratio": 0.08262116728508409,
      "rank": 9
    },
    {
      "symbol": "ADA",
      "name": "Cardano",
      "price": 0.28037763776409713,
      "volume_24h": 349262347.40768886,
      "market_cap": 10113167894.546274,
      "vol_mcap_ratio": 0.03453540483551504,
      "rank": 10
    },
    {
      "symbol": "BCH",
      "name": "Bitcoin Cash",
      "price": 566.2634186182726,
      "volume_24h": 313726622.1561862,
      "market_cap": 11324211937.17509,
      "vol_mcap_ratio": 0.02770405780964637,
      "rank": 11
    },
    {
      "symbol": "SUI",
      "name": "Sui",
      "price": 0.9462280063356336,
      "volume_24h": 377085064.23739517,
      "market_cap": 3639356162.6526575,
      "vol_mcap_ratio": 0.10361312479033243,
      "rank": 12
    },
    {
      "symbol": "VBNB",
      "name": "Venus BNB",
      "price": 15.564588383340102,
      "volume_24h": 415046630.43801045,
      "market_cap": 414990439.30978405,
      "vol_mcap_ratio": 1.0001354034283774,
      "rank": 13
    },
    {
      "symbol": "LTC",
      "name": "Litecoin",
      "price": 55.68775856923246,
      "volume_24h": 297788248.43866915,
      "market_cap": 4280941558.8032317,
      "vol_mcap_ratio": 0.06956139072403456,
      "rank": 14
    },
    {
      "symbol": "AAVE",
      "name": "Aave",
      "price": 121.59150591255863,
      "volume_24h": 383142376.4254543,
      "market_cap": 1863848366.1780899,
      "vol_mcap_ratio": 0.205565207652115,
      "rank": 15
    },
    {
      "symbol": "ZEC",
      "name": "Zcash",
      "price": 258.68328220427117,
      "volume_24h": 236744554.2501266,
      "market_cap": 4280126129.457848,
      "vol_mcap_ratio": 0.055312518157055894,
      "rank": 16
    },
    {
      "symbol": "HYPE",
      "name": "Hyperliquid",
      "price": 29.724605869755035,
      "volume_24h": 140813328.63811073,
      "market_cap": 7696115541.716703,
      "vol_mcap_ratio": 0.018296675494908276,
      "rank": 17
    },
    {
      "symbol": "AVAX",
      "name": "Avalanche",
      "price": 9.218583899218897,
      "volume_24h": 195237206.43541086,
      "market_cap": 3980326049.4424124,
      "vol_mcap_ratio": 0.049050556163046204,
      "rank": 18
    },
    {
      "symbol": "PEPE",
      "name": "Pepe",
      "price": 4.191364896550735e-06,
      "volume_24h": 268981846.176769,
      "market_cap": 1734271538.0178728,
      "vol_mcap_ratio": 0.1550978842011054,
      "rank": 19
    },
    {
      "symbol": "USDS",
      "name": "USDS",
      "price": 1.0000430353107366,
      "volume_24h": 98491801.5567053,
      "market_cap": 9894720084.929932,
      "vol_mcap_ratio": 0.009953975525463564,
      "rank": 20
    }
  ]
}