{
  "updated_utc": "2026-02-17T20:39:13Z",
  "criteria": "CMC-only | Exclude stable/wrapped | MarketCap>=200000000 | Volume24h>=20000000 | Score=log(vol)+0.7log(mcap)+ratio(clamped)-penalty",
  "items": [
    {
      "symbol": "BTC",
      "name": "Bitcoin",
      "price": 67626.74048384008,
      "volume_24h": 35918718150.7763,
      "market_cap": 1351915145853.7483,
      "vol_mcap_ratio": 0.02656876673135669,
      "rank": 1
    },
    {
      "symbol": "ETH",
      "name": "Ethereum",
      "price": 1992.2732740022184,
      "volume_24h": 21199860028.61566,
      "market_cap": 240452323525.3903,
      "vol_mcap_ratio": 0.08816658420178287,
      "rank": 2
    },
    {
      "symbol": "XRP",
      "name": "XRP",
      "price": 1.479524012915292,
      "volume_24h": 2394196076.381856,
      "market_cap": 90128630864.13783,
      "vol_mcap_ratio": 0.026564212209003013,
      "rank": 3
    },
    {
      "symbol": "SOL",
      "name": "Solana",
      "price": 84.87715440872674,
      "volume_24h": 3238070486.9563503,
      "market_cap": 48227218994.59733,
      "vol_mcap_ratio": 0.0671419699178403,
      "rank": 4
    },
    {
      "symbol": "BNB",
      "name": "BNB",
      "price": 617.770294164051,
      "volume_24h": 1327968842.7529066,
      "market_cap": 84238658505.94138,
      "vol_mcap_ratio": 0.015764363610553514,
      "rank": 5
    },
    {
      "symbol": "USD1",
      "name": "World Liberty Financial USD",
      "price": 0.9995582827103431,
      "volume_24h": 2696738078.709045,
      "market_cap": 5135514506.417031,
      "vol_mcap_ratio": 0.5251154631808288,
      "rank": 6
    },
    {
      "symbol": "DOGE",
      "name": "Dogecoin",
      "price": 0.10072960254049566,
      "volume_24h": 1034152601.5286933,
      "market_cap": 17001303799.08799,
      "vol_mcap_ratio": 0.060827840837957906,
      "rank": 7
    },
    {
      "symbol": "TRX",
      "name": "TRON",
      "price": 0.28211615120352274,
      "volume_24h": 608812263.2116427,
      "market_cap": 26723997629.03929,
      "vol_mcap_ratio": 0.022781481710284417,
      "rank": 8
    },
    {
      "symbol": "LINK",
      "name": "Chainlink",
      "price": 8.843248656929962,
      "volume_24h": 566428711.7215046,
      "market_cap": 6261904112.676983,
      "vol_mcap_ratio": 0.09045630554686897,
      "rank": 9
    },
    {
      "symbol": "BCH",
      "name": "Bitcoin Cash",
      "price": 567.7234375230422,
      "volume_24h": 375357148.29160225,
      "market_cap": 11352313175.533998,
      "vol_mcap_ratio": 0.03306437573450276,
      "rank": 10
    },
    {
      "symbol": "ADA",
      "name": "Cardano",
      "price": 0.2821296107063442,
      "volume_24h": 392812347.6797597,
      "market_cap": 10175327504.007647,
      "vol_mcap_ratio": 0.038604393571120624,
      "rank": 11
    },
    {
      "symbol": "SUI",
      "name": "Sui",
      "price": 0.9651985637806025,
      "volume_24h": 519429266.2438782,
      "market_cap": 3712320199.5275235,
      "vol_mcap_ratio": 0.13992038356766404,
      "rank": 12
    },
    {
      "symbol": "ZEC",
      "name": "Zcash",
      "price": 285.1646603547778,
      "volume_24h": 345900078.82375646,
      "market_cap": 4716567886.7212,
      "vol_mcap_ratio": 0.07333724164080983,
      "rank": 13
    },
    {
      "symbol": "XAUT",
      "name": "Tether Gold",
      "price": 4854.933656548193,
      "volume_24h": 433300968.79577,
      "market_cap": 2528573937.068075,
      "vol_mcap_ratio": 0.17136179505915097,
      "rank": 14
    },
    {
      "symbol": "LTC",
      "name": "Litecoin",
      "price": 54.039294076981825,
      "volume_24h": 322350778.2959853,
      "market_cap": 4153482878.8966093,
      "vol_mcap_ratio": 0.07760975251247916,
      "rank": 15
    },
    {
      "symbol": "VBNB",
      "name": "Venus BNB",
      "price": 15.395693389683961,
      "volume_24h": 411168331.48231614,
      "market_cap": 411169497.376501,
      "vol_mcap_ratio": 0.9999971644438794,
      "rank": 16
    },
    {
      "symbol": "HYPE",
      "name": "Hyperliquid",
      "price": 29.552265784979006,
      "volume_24h": 216831678.64600646,
      "market_cap": 7658293476.786521,
      "vol_mcap_ratio": 0.02831331540156525,
      "rank": 17
    },
    {
      "symbol": "PEPE",
      "name": "Pepe",
      "price": 4.388955241088113e-06,
      "volume_24h": 382571840.6178202,
      "market_cap": 1816028989.152782,
      "vol_mcap_ratio": 0.21066395024690576,
      "rank": 18
    },
    {
      "symbol": "PAXG",
      "name": "PAX Gold",
      "price": 4879.29158972707,
      "volume_24h": 341123759.2701954,
      "market_cap": 2239643510.6183324,
      "vol_mcap_ratio": 0.15231163247762416,
      "rank": 19
    },
    {
      "symbol": "AAVE",
      "name": "Aave",
      "price": 126.71029798969914,
      "volume_24h": 352414644.5345225,
      "market_cap": 1942267114.3652961,
      "vol_mcap_ratio": 0.18144499380544077,
      "rank": 20
    }
  ]
}