{
  "updated_utc": "2026-02-17T13:24:45Z",
  "criteria": "CMC-only | Exclude stable/wrapped | MarketCap>=200000000 | Volume24h>=20000000 | Score=log(vol)+0.7log(mcap)+ratio(clamped)-penalty",
  "items": [
    {
      "symbol": "BTC",
      "name": "Bitcoin",
      "price": 68090.17284175391,
      "volume_24h": 31615427577.120358,
      "market_cap": 1361179546581.3293,
      "vol_mcap_ratio": 0.023226493269403063,
      "rank": 1
    },
    {
      "symbol": "ETH",
      "name": "Ethereum",
      "price": 1984.406099168439,
      "volume_24h": 17886008124.68873,
      "market_cap": 239502814995.0858,
      "vol_mcap_ratio": 0.07467974071643259,
      "rank": 2
    },
    {
      "symbol": "XRP",
      "name": "XRP",
      "price": 1.4552617998536337,
      "volume_24h": 2277668030.958636,
      "market_cap": 88650641979.94765,
      "vol_mcap_ratio": 0.025692628728778224,
      "rank": 3
    },
    {
      "symbol": "SOL",
      "name": "Solana",
      "price": 84.88672428793734,
      "volume_24h": 3147020297.40076,
      "market_cap": 48222313156.44842,
      "vol_mcap_ratio": 0.06526066651325564,
      "rank": 4
    },
    {
      "symbol": "BNB",
      "name": "BNB",
      "price": 621.4921332491873,
      "volume_24h": 1325551731.2156715,
      "market_cap": 84746172265.16013,
      "vol_mcap_ratio": 0.015641434837530912,
      "rank": 5
    },
    {
      "symbol": "USD1",
      "name": "World Liberty Financial USD",
      "price": 0.9997666339784431,
      "volume_24h": 2561619446.03368,
      "market_cap": 5149958697.830334,
      "vol_mcap_ratio": 0.49740582329580324,
      "rank": 6
    },
    {
      "symbol": "DOGE",
      "name": "Dogecoin",
      "price": 0.10003924182749818,
      "volume_24h": 992461598.7649807,
      "market_cap": 16884384454.637781,
      "vol_mcap_ratio": 0.05877985078054608,
      "rank": 7
    },
    {
      "symbol": "TRX",
      "name": "TRON",
      "price": 0.28118073080113476,
      "volume_24h": 584739737.2557195,
      "market_cap": 26635423809.80236,
      "vol_mcap_ratio": 0.021953460978553073,
      "rank": 8
    },
    {
      "symbol": "BCH",
      "name": "Bitcoin Cash",
      "price": 562.9590577746309,
      "volume_24h": 372967055.56513596,
      "market_cap": 11256957467.214407,
      "vol_mcap_ratio": 0.03313213687192056,
      "rank": 9
    },
    {
      "symbol": "LINK",
      "name": "Chainlink",
      "price": 8.815164276191394,
      "volume_24h": 505859200.15071476,
      "market_cap": 6242017563.505824,
      "vol_mcap_ratio": 0.08104097673614993,
      "rank": 10
    },
    {
      "symbol": "ADA",
      "name": "Cardano",
      "price": 0.2826869646554991,
      "volume_24h": 384290165.47604126,
      "market_cap": 10195429112.46379,
      "vol_mcap_ratio": 0.03769239737111713,
      "rank": 11
    },
    {
      "symbol": "SUI",
      "name": "Sui",
      "price": 0.9728170276292066,
      "volume_24h": 502335821.452587,
      "market_cap": 3741622125.8832407,
      "vol_mcap_ratio": 0.1342561607110463,
      "rank": 12
    },
    {
      "symbol": "ZEC",
      "name": "Zcash",
      "price": 290.9243284263989,
      "volume_24h": 352511199.31844765,
      "market_cap": 4811717667.752862,
      "vol_mcap_ratio": 0.0732609898708116,
      "rank": 13
    },
    {
      "symbol": "VBNB",
      "name": "Venus BNB",
      "price": 15.47529389241595,
      "volume_24h": 413321125.2794394,
      "market_cap": 413813504.8923779,
      "vol_mcap_ratio": 0.9988101412662533,
      "rank": 14
    },
    {
      "symbol": "LTC",
      "name": "Litecoin",
      "price": 54.88578899290644,
      "volume_24h": 308482037.1642264,
      "market_cap": 4218486175.0963335,
      "vol_mcap_ratio": 0.07312624111116872,
      "rank": 15
    },
    {
      "symbol": "PEPE",
      "name": "Pepe",
      "price": 4.431673774947811e-06,
      "volume_24h": 401727858.00625414,
      "market_cap": 1833704743.7690632,
      "vol_mcap_ratio": 0.21907990333303504,
      "rank": 16
    },
    {
      "symbol": "HYPE",
      "name": "Hyperliquid",
      "price": 29.55175709930176,
      "volume_24h": 195953142.26702744,
      "market_cap": 7659230927.4945755,
      "vol_mcap_ratio": 0.02558391881926532,
      "rank": 17
    },
    {
      "symbol": "AAVE",
      "name": "Aave",
      "price": 126.95726997889025,
      "volume_24h": 372010636.5221744,
      "market_cap": 1946035322.1319685,
      "vol_mcap_ratio": 0.19116335263361003,
      "rank": 18
    },
    {
      "symbol": "XAUT",
      "name": "Tether Gold",
      "price": 4898.35168994038,
      "volume_24h": 290649263.60499716,
      "market_cap": 2551187162.1756816,
      "vol_mcap_ratio": 0.11392706419748841,
      "rank": 19
    },
    {
      "symbol": "PAXG",
      "name": "PAX Gold",
      "price": 4923.487598469398,
      "volume_24h": 237829009.63496011,
      "market_cap": 2259929919.4862485,
      "vol_mcap_ratio": 0.10523733837243322,
      "rank": 20
    }
  ]
}