{
  "updated_utc": "2026-01-26T20:53:04Z",
  "criteria": "Ranked by combined score: 24h Volume + (Volume/MarketCap ratio)",
  "items": [
    {
      "symbol": "TIMI",
      "name": "MetaArena",
      "price": 0.004574620560904276,
      "volume_24h": 861166831.1766871,
      "market_cap": 1821836.2842321687,
      "vol_mcap_ratio": 472.69166753896036,
      "rank": 1
    },
    {
      "symbol": "USDT",
      "name": "Tether USDt",
      "price": 0.9987827796711157,
      "volume_24h": 104083858514.65868,
      "market_cap": 186646335667.5699,
      "vol_mcap_ratio": 0.55765283653915,
      "rank": 2
    },
    {
      "symbol": "BTC",
      "name": "Bitcoin",
      "price": 87585.57117275977,
      "volume_24h": 48364563945.259796,
      "market_cap": 1750037400433.3704,
      "vol_mcap_ratio": 0.02763630304888515,
      "rank": 3
    },
    {
      "symbol": "QUQ",
      "name": "Quq",
      "price": 0.0021975439235899226,
      "volume_24h": 281137417.9428909,
      "market_cap": 2197543.9235899225,
      "vol_mcap_ratio": 127.93255912884003,
      "rank": 4
    },
    {
      "symbol": "ETH",
      "name": "Ethereum",
      "price": 2906.1114610742193,
      "volume_24h": 31090113339.22741,
      "market_cap": 350751433793.56604,
      "vol_mcap_ratio": 0.0886385923015939,
      "rank": 5
    },
    {
      "symbol": "OWL",
      "name": "Owlto Finance",
      "price": 0.05213998557830241,
      "volume_24h": 1583792840.5788226,
      "market_cap": 17206195.240839798,
      "vol_mcap_ratio": 92.04782454284884,
      "rank": 6
    },
    {
      "symbol": "USDC",
      "name": "USDC",
      "price": 0.9995246327150318,
      "volume_24h": 14359061114.939842,
      "market_cap": 72123915046.26974,
      "vol_mcap_ratio": 0.1990887641876908,
      "rank": 7
    },
    {
      "symbol": "FDUSD",
      "name": "First Digital USD",
      "price": 0.997354409988863,
      "volume_24h": 3866069909.776041,
      "market_cap": 495245674.60790074,
      "vol_mcap_ratio": 7.8063678452859016,
      "rank": 8
    },
    {
      "symbol": "DONT",
      "name": "DisclaimerCoin",
      "price": 1.1089751468789927e-05,
      "volume_24h": 29788951.44938269,
      "market_cap": 1414594.5029039518,
      "vol_mcap_ratio": 21.05829719275058,
      "rank": 9
    },
    {
      "symbol": "SOL",
      "name": "Solana",
      "price": 123.70463856167294,
      "volume_24h": 4918058071.412361,
      "market_cap": 70010337060.50212,
      "vol_mcap_ratio": 0.07024759882475973,
      "rank": 10
    },
    {
      "symbol": "POWER",
      "name": "Power Protocol",
      "price": 0.2095554802829812,
      "volume_24h": 703611249.333578,
      "market_cap": 44006650.85942605,
      "vol_mcap_ratio": 15.988747964056147,
      "rank": 11
    },
    {
      "symbol": "IR",
      "name": "Infrared",
      "price": 0.057004130471114335,
      "volume_24h": 196708545.78643337,
      "market_cap": 11685846.746578438,
      "vol_mcap_ratio": 16.83305883196087,
      "rank": 12
    },
    {
      "symbol": "ENSO",
      "name": "Enso",
      "price": 1.3928336038605948,
      "volume_24h": 393555124.8332762,
      "market_cap": 28678443.90348965,
      "vol_mcap_ratio": 13.723029260502786,
      "rank": 13
    },
    {
      "symbol": "XRP",
      "name": "XRP",
      "price": 1.8943291654902397,
      "volume_24h": 3225972863.1919327,
      "market_cap": 115276054722.76772,
      "vol_mcap_ratio": 0.027984761197372792,
      "rank": 14
    },
    {
      "symbol": "USDQ",
      "name": "Quantoz USDQ",
      "price": 0.9993897873426474,
      "volume_24h": 81970747.46845219,
      "market_cap": 7975179.4730939055,
      "vol_mcap_ratio": 10.278232326306796,
      "rank": 15
    },
    {
      "symbol": "USD1",
      "name": "World Liberty Financial USD",
      "price": 0.9993425703743479,
      "volume_24h": 2218594858.438137,
      "market_cap": 4928827568.083372,
      "vol_mcap_ratio": 0.4501262882078996,
      "rank": 16
    },
    {
      "symbol": "BNB",
      "name": "BNB",
      "price": 872.1081636475537,
      "volume_24h": 2197048687.2983203,
      "market_cap": 118921005445.00401,
      "vol_mcap_ratio": 0.01847485798725746,
      "rank": 17
    },
    {
      "symbol": "NOM",
      "name": "Nomina",
      "price": 0.011111692225169301,
      "volume_24h": 216705495.81896412,
      "market_cap": 32223907.45299097,
      "vol_mcap_ratio": 6.724991254865643,
      "rank": 18
    },
    {
      "symbol": "ELSA",
      "name": "HeyElsa",
      "price": 0.11408885801257218,
      "volume_24h": 170193961.84941322,
      "market_cap": 26124066.70771878,
      "vol_mcap_ratio": 6.514834147132485,
      "rank": 19
    },
    {
      "symbol": "AUCTION",
      "name": "Bounce Token",
      "price": 6.471880059905713,
      "volume_24h": 257046466.13344714,
      "market_cap": 42651926.42332687,
      "vol_mcap_ratio": 6.02660858931017,
      "rank": 20
    }
  ]
}